LICENSE
README.md
pyproject.toml
setup.cfg
setup.py
pymbxas/__init__.py
pymbxas/spectra.py
pymbxas/spectras.py
pymbxas.egg-info/PKG-INFO
pymbxas.egg-info/SOURCES.txt
pymbxas.egg-info/dependency_links.txt
pymbxas.egg-info/requires.txt
pymbxas.egg-info/top_level.txt
pymbxas/build/__init__.py
pymbxas/build/input.py
pymbxas/build/input_pyscf.py
pymbxas/build/structure.py
pymbxas/calculators/__init__.py
pymbxas/calculators/excitation.py
pymbxas/calculators/pyscf.py
pymbxas/calculators/qchem.py
pymbxas/cli/__init__.py
pymbxas/cli/main.py
pymbxas/explorer/__init__.py
pymbxas/explorer/mbxasplorer.py
pymbxas/explorer/node.py
pymbxas/explorer/pca.py
pymbxas/io/__init__.py
pymbxas/io/cleanup.py
pymbxas/io/copy.py
pymbxas/io/data.py
pymbxas/io/logger.py
pymbxas/io/read.py
pymbxas/io/run.py
pymbxas/io/write.py
pymbxas/mbxas/__init__.py
pymbxas/mbxas/broaden.py
pymbxas/mbxas/mbxas.py
pymbxas/md/__init__.py
pymbxas/md/callback.py
pymbxas/md/integrator.py
pymbxas/md/solvers.py
pymbxas/tools/__init__.py
pymbxas/tools/geometry.py
pymbxas/utils/__init__.py
pymbxas/utils/auxiliary.py
pymbxas/utils/basis.py
pymbxas/utils/boys.py
pymbxas/utils/check_keywords.py
pymbxas/utils/environment.py
pymbxas/utils/indexing.py
pymbxas/utils/metrics.py
pymbxas/utils/orbitals.py
pymbxas/utils/test_livos.py