Metadata-Version: 2.1
Name: pymbxas
Version: 0.5.0
Summary: PyMBXAS is a package for setting up, manipulating, running and visualizing MBXAS calculations using Python.
Home-page: https://gitlab.com/roncofaber/pymbxas
Author: Fabrice Roncoroni
Author-email: roncoroni@lbl.gov
License: Apache-2.0
Classifier: Programming Language :: Python :: 3
Classifier: License :: OSI Approved :: Apache Software License
Classifier: Operating System :: OS Independent
Classifier: Topic :: Software Development
Classifier: Topic :: Scientific/Engineering
Requires-Python: >=3.6
License-File: LICENSE
Requires-Dist: pyscf>=2.6.2
Requires-Dist: ase>=3.23.0
Requires-Dist: dill>=0.3.8
Requires-Dist: psutil
Requires-Dist: numpy<2.0.0
